data_source_local/__init__.py
data_source_local/src/__init__.py
data_source_local/src/data_source.py
data_source_local/src/data_source_constans.py
data_source_local/src/data_source_enum.py
source_data_local-0.0.7.dist-info/METADATA
source_data_local-0.0.7.dist-info/WHEEL
source_data_local-0.0.7.dist-info/top_level.txt
source_data_local-0.0.7.dist-info/RECORD
